muyi/__init__.py
muyi/gpu.py
muyi/graph.py
muyi/utils.py
Muyi-0.0.8.dist-info/LICENSE
Muyi-0.0.8.dist-info/METADATA
Muyi-0.0.8.dist-info/WHEEL
Muyi-0.0.8.dist-info/top_level.txt
Muyi-0.0.8.dist-info/RECORD
