Metadata-Version: 2.1
Name: Muyi
Version: 0.0.8
Summary: Some useful utils.
Home-page: https://github.com/Muyiiiii/muyi
Author: muyiiiii
Author-email: 
Classifier: Programming Language :: Python :: 3
Classifier: License :: OSI Approved :: MIT License
Classifier: Operating System :: OS Independent
Requires-Python: >=3
License-File: LICENSE
